{
    "Page":
    {
        "name":"n6",
        "caption":"历任董高监",
        "Request":
        [
            {
                "responsetype":"rtDataTable",
                "cdatasection":
                {
                    "ConditionOne":"1",
                    "SecuCode":"SecuCode",
                    "ApiName":"Bond.F9.Abs.Reimb_order.ReimbursementOrder"
                }

            },
            {
                "responsetype":"rtDataTable",
                "cdatasection":
                {
                    "ConditionOne":"2",
                    "SecuCode":"SecuCode",
                    "ApiName":"Bond.F9.Abs.Reimb_order.ReimbursementOrder"
                }

            },
            {
                "responsetype":"rtDataTable",
                "cdatasection":
                {
                    "ConditionOne":"3",
                    "SecuCode":"SecuCode",
                    "ApiName":"Bond.F9.Abs.Reimb_order.ReimbursementOrder"
                }

            }

        ],
        "content":
        [
            {
                "tag":"ToolBar",
                "attrs":
                {
                    "name":"lcToolbar"
                },
                "children":
                [
                    {
                        "tag":"Button",
                        "attrs":
                        {
                            "name":"btnRequest"
                        },
                        "children":
                        [
                            
                        ]

                    },
                    {
                        "tag":"Button",
                        "attrs":
                        {
                            "name":"btnOutput",
                            "caption":"数据导出",
                            "bindvalue":"OUTPUT",
                            "imageIndex":"9"
                        },
                        "children":
                        [
                            
                        ]

                    }

                ]

            },
            {
                "tag":"Container",
                "attrs":
                {
                    "name":"ctReport0",
                    "caption":"报表容器",
                    "borderSides":"0"
                },
                "children":
                [
                    {
                        "tag":"SheetControl",
                        "attrs":
                        {
                            "name":"scTable",
                            "sheetCount":"3",
                            "tabWidth":"150",
                            "sheetContent":
                            [
                                {
                                    "name":"shtitem1",
                                    "caption":"违约前",
                                    "show":true
                                },
                                {
                                    "name":"shtitem2",
                                    "caption":"违约后",
                                    "show":false
                                },
                                {
                                    "name":"shtitem3",
                                    "caption":"信托终止后",
                                    "show":false
                                }

                            ]

                        },
                        "children":
                        [
                            {
                                "tag":"SheetItem",
                                "attrs":
                                {
                                    "name":"shtitem1",
                                    "caption":"违约前",
                                    "show":true
                                },
                                "children":
                                [
                                    {
                                        "tag":"Container",
                                        "attrs":
                                        {
                                            "name":"ctReport1",
                                            "caption":"报表容器",
                                            "borderSides":"0"
                                        },
                                        "children":
                                        [
                                            {
                                                "tag":"Report",
                                                "attrs":
                                                {
                                                    "name":"rpt1",
                                                    "tablename":"Bond.F9.Abs.Reimb_order.ReimbursementOrder",
                                                    "caption":"公司概况",
                                                    "tag_column":
                                                    [
                                                        {
                                                            "fieldname":"A0",
                                                            "caption":"偿付顺序"
                                                        },
                                                        {
                                                            "fieldname":"A1",
                                                            "caption":"事件一"
                                                        },
                                                        {
                                                            "fieldname":"A2",
                                                            "caption":"事件二"
                                                        },
                                                        {
                                                            "fieldname":"A3",
                                                            "caption":"收益账户"
                                                        },
                                                        {
                                                            "fieldname":"A4",
                                                            "caption":"付款账户"
                                                        },
                                                        {
                                                            "fieldname":"A5",
                                                            "caption":"关联债券"
                                                        },
                                                        {
                                                            "fieldname":"A6",
                                                            "caption":"偿付项目"
                                                        },
                                                        {
                                                            "fieldname":"A7",
                                                            "caption":"金额限制"
                                                        },
                                                        {
                                                            "fieldname":"A8",
                                                            "caption":"限制描述"
                                                        },
                                                        {
                                                            "fieldname":"A9",
                                                            "caption":"是否包括累计未付"
                                                        },
                                                        {
                                                            "fieldname":"B0",
                                                            "caption":"偿付顺序描述"
                                                        }

                                                    ]

                                                },
                                                "children":
                                                [
                                                    
                                                ]

                                            }

                                        ]

                                    }

                                ]

                            },
                            {
                                "tag":"SheetItem",
                                "attrs":
                                {
                                    "name":"shtitem2",
                                    "caption":"违约后",
                                    "show":false
                                },
                                "children":
                                [
                                    {
                                        "tag":"Container",
                                        "attrs":
                                        {
                                            "name":"ctReport2",
                                            "caption":"报表容器",
                                            "borderSides":"1",
                                            "padding":"0"
                                        },
                                        "children":
                                        [
                                            {
                                                "tag":"Report",
                                                "attrs":
                                                {
                                                    "name":"rpt2",
                                                    "apiindex":"1",
                                                    "tablename":"Bond.F9.Abs.Reimb_order.ReimbursementOrder",
                                                    "caption":"变更项目",
                                                    "tag_column":
                                                    [
                                                        {
                                                            "fieldname":"A0",
                                                            "caption":"偿付顺序"
                                                        },
                                                        {
                                                            "fieldname":"A1",
                                                            "caption":"事件一"
                                                        },
                                                        {
                                                            "fieldname":"A2",
                                                            "caption":"事件二"
                                                        },
                                                        {
                                                            "fieldname":"A3",
                                                            "caption":"收益账户"
                                                        },
                                                        {
                                                            "fieldname":"A4",
                                                            "caption":"付款账户"
                                                        },
                                                        {
                                                            "fieldname":"A5",
                                                            "caption":"关联债券"
                                                        },
                                                        {
                                                            "fieldname":"A6",
                                                            "caption":"偿付项目"
                                                        },
                                                        {
                                                            "fieldname":"A7",
                                                            "caption":"金额限制"
                                                        },
                                                        {
                                                            "fieldname":"A8",
                                                            "caption":"限制描述"
                                                        },
                                                        {
                                                            "fieldname":"A9",
                                                            "caption":"是否包括累计未付"
                                                        },
                                                        {
                                                            "fieldname":"B0",
                                                            "caption":"偿付顺序描述"
                                                        }

                                                    ]

                                                },
                                                "children":
                                                [
                                                    
                                                ]

                                            }

                                        ]

                                    }

                                ]

                            },
                            {
                                "tag":"SheetItem",
                                "attrs":
                                {
                                    "name":"shtitem3",
                                    "caption":"信托终止后",
                                    "show":false
                                },
                                "children":
                                [
                                    {
                                        "tag":"Container",
                                        "attrs":
                                        {
                                            "name":"ctReport3",
                                            "caption":"信托终止后",
                                            "padding":"0",
                                            "borderSides":"0"
                                        },
                                        "children":
                                        [
                                            {
                                                "tag":"Report",
                                                "attrs":
                                                {
                                                    "name":"rpt3",
                                                    "apiindex":"2",
                                                    "tablename":"Bond.F9.Abs.Reimb_order.ReimbursementOrder",
                                                    "caption":"变更项目",
                                                    "tag_column":
                                                    [
                                                        {
                                                            "fieldname":"A0",
                                                            "caption":"偿付顺序"
                                                        },
                                                        {
                                                            "fieldname":"A1",
                                                            "caption":"事件一"
                                                        },
                                                        {
                                                            "fieldname":"A2",
                                                            "caption":"事件二"
                                                        },
                                                        {
                                                            "fieldname":"A3",
                                                            "caption":"收益账户"
                                                        },
                                                        {
                                                            "fieldname":"A4",
                                                            "caption":"付款账户"
                                                        },
                                                        {
                                                            "fieldname":"A5",
                                                            "caption":"关联债券"
                                                        },
                                                        {
                                                            "fieldname":"A6",
                                                            "caption":"偿付项目"
                                                        },
                                                        {
                                                            "fieldname":"A7",
                                                            "caption":"金额限制"
                                                        },
                                                        {
                                                            "fieldname":"A8",
                                                            "caption":"限制描述"
                                                        },
                                                        {
                                                            "fieldname":"A9",
                                                            "caption":"是否包括累计未付"
                                                        },
                                                        {
                                                            "fieldname":"B0",
                                                            "caption":"偿付顺序描述"
                                                        }

                                                    ]

                                                },
                                                "children":
                                                [
                                                    
                                                ]

                                            }

                                        ]

                                    }

                                ]

                            }

                        ]

                    }

                ]

            }

        ]

    }

}