{
    "Page":
    {
        "name":"JYTopic.StockSecondaryMarket.TransferParticipantsReport",
        "caption":"转融通参与人名单",
        "Request":
        [
            {
                "responsetype":"rtDataTable",
                "cdatasection":
                {
                    "ApiName":"JYTopic.StockSecondaryMarket.TransferParticipantsReport"
                }

            }

        ],
        "content":
        [
            {
                "tag":"ToolBar",
                "attrs":
                {
                    "name":"lcToolbar"
                },
                "children":
                [
                    {
                        "tag":"Button",
                        "attrs":
                        {
                            "name":"btnRequest"
                        },
                        "children":
                        [
                            
                        ]

                    },
                    {
                        "tag":"Button",
                        "attrs":
                        {
                            "name":"btnOutput",
                            "caption":"数据导出",
                            "bindvalue":"OUTPUT",
                            "imageIndex":"9"
                        },
                        "children":
                        [
                            
                        ]

                    }

                ]

            },
            {
                "tag":"Container",
                "attrs":
                {
                    "name":"ctGrd1",
                    "caption":"报表容器",
                    "borderSides":"0"
                },
                "children":
                [
                    {
                        "tag":"Container",
                        "attrs":
                        {
                            "name":"ctPd2",
                            "caption":"报表容器",
                            "padding":"0"
                        },
                        "children":
                        [
                            {
                                "tag":"Report",
                                "attrs":
                                {
                                    "name":"rpt1",
                                    "tablename":"JYTopic.StockSecondaryMarket.TransferParticipantsReport",
                                    "caption":"转融通参与人名单",
                                    "defselect":true,
                                    "fixedcount":"3",
                                    "type":
                                    [
                                        {
                                            "fieldname":"NonamedIndex",
                                            "type":"index"
                                        }

                                    ],
                                    "tag_row":
                                    [
                                        {
                                            "rname":"caption",
                                            "heigh":"100",
                                            "algmt":"taLeftJustify"
                                        }

                                    ],
                                    "tag_column":
                                    [
                                        {
                                            "fieldname":"A0",
                                            "caption":"公司名称"
                                        },
                                        {
                                            "fieldname":"A1",
                                            "caption":"公司简称"
                                        },
                                        {
                                            "caption":"生效日期",
                                            "tag_column":
                                            [
                                                {
                                                    "fieldname":"A2",
                                                    "caption":"转融资借入人"
                                                },
                                                {
                                                    "fieldname":"A3",
                                                    "caption":"转融券借入人"
                                                },
                                                {
                                                    "fieldname":"A4",
                                                    "caption":"代理证券公司"
                                                }

                                            ]

                                        },
                                        {
                                            "fieldname":"A5",
                                            "caption":"历史明细",
                                            "functype":"ftmemo"
                                        }

                                    ]

                                },
                                "children":
                                [
                                    
                                ]

                            }

                        ]

                    }

                ]

            }

        ]

    }

}